datakit_data/__init__.py
datakit_data/extra_flags.py
datakit_data/project_mixin.py
datakit_data/s3.py
datakit_data/commands/__init__.py
datakit_data/commands/init.py
datakit_data/commands/pull.py
datakit_data/commands/push.py
datakit_data-0.3.0.dist-info/AUTHORS.rst
datakit_data-0.3.0.dist-info/LICENSE
datakit_data-0.3.0.dist-info/METADATA
datakit_data-0.3.0.dist-info/WHEEL
datakit_data-0.3.0.dist-info/entry_points.txt
datakit_data-0.3.0.dist-info/top_level.txt
datakit_data-0.3.0.dist-info/RECORD
