Metadata-Version: 2.1
Name: datakit-data
Version: 0.3.0
Summary: A datakit plugin to manage data assets on AWS S3.
Home-page: https://github.com/associatedpress/datakit-data
Author: Serdar Tumgoren
Author-email: stumgoren@ap.org
License: ISC license
Keywords: datakit
Platform: UNKNOWN
Classifier: Development Status :: 3 - Alpha
Classifier: Environment :: Console
Classifier: Intended Audience :: Developers
Classifier: License :: OSI Approved :: ISC License (ISCL)
Classifier: Natural Language :: English
Classifier: Programming Language :: Python :: 3
Classifier: Programming Language :: Python :: 3.3
Classifier: Programming Language :: Python :: 3.4
Classifier: Programming Language :: Python :: 3.5
Classifier: Programming Language :: Python :: 3.6
Requires-Dist: awscli
Requires-Dist: cliff
Requires-Dist: datakit-core (>=0.2.1)
